{
    "name": "root",
    "gauges": {
        "CarAgent.Policy.Entropy.mean": {
            "value": 1.468895673751831,
            "min": 1.4189382791519165,
            "max": 1.468895673751831,
            "count": 5
        },
        "CarAgent.Policy.Entropy.sum": {
            "value": 1504.149169921875,
            "min": 1387.66796875,
            "max": 1522.52099609375,
            "count": 5
        },
        "CarAgent.Step.mean": {
            "value": 4992.0,
            "min": 960.0,
            "max": 4992.0,
            "count": 5
        },
        "CarAgent.Step.sum": {
            "value": 4992.0,
            "min": 960.0,
            "max": 4992.0,
            "count": 5
        },
        "CarAgent.Policy.ExtrinsicValueEstimate.mean": {
            "value": 0.0,
            "min": 0.0,
            "max": 0.0,
            "count": 5
        },
        "CarAgent.Policy.ExtrinsicValueEstimate.sum": {
            "value": 0.0,
            "min": 0.0,
            "max": 0.0,
            "count": 5
        },
        "CarAgent.IsTraining.mean": {
            "value": 1.0,
            "min": 1.0,
            "max": 1.0,
            "count": 5
        },
        "CarAgent.IsTraining.sum": {
            "value": 1.0,
            "min": 1.0,
            "max": 1.0,
            "count": 5
        },
        "CarAgent.Losses.PolicyLoss.mean": {
            "value": 0.0,
            "min": 0.0,
            "max": 0.0,
            "count": 2
        },
        "CarAgent.Losses.PolicyLoss.sum": {
            "value": 0.0,
            "min": 0.0,
            "max": 0.0,
            "count": 2
        },
        "CarAgent.Losses.ValueLoss.mean": {
            "value": 0.0,
            "min": 0.0,
            "max": 0.0,
            "count": 2
        },
        "CarAgent.Losses.ValueLoss.sum": {
            "value": 0.0,
            "min": 0.0,
            "max": 0.0,
            "count": 2
        },
        "CarAgent.Policy.LearningRate.mean": {
            "value": 0.00027465600844799997,
            "min": 0.00027465600844799997,
            "max": 0.00028732800422399995,
            "count": 2
        },
        "CarAgent.Policy.LearningRate.sum": {
            "value": 0.00027465600844799997,
            "min": 0.00027465600844799997,
            "max": 0.00028732800422399995,
            "count": 2
        },
        "CarAgent.Policy.Epsilon.mean": {
            "value": 0.19155200000000003,
            "min": 0.19155200000000003,
            "max": 0.19577599999999995,
            "count": 2
        },
        "CarAgent.Policy.Epsilon.sum": {
            "value": 0.19155200000000003,
            "min": 0.19155200000000003,
            "max": 0.19577599999999995,
            "count": 2
        },
        "CarAgent.Policy.Beta.mean": {
            "value": 0.0045784448,
            "min": 0.0045784448,
            "max": 0.004789222400000001,
            "count": 2
        },
        "CarAgent.Policy.Beta.sum": {
            "value": 0.0045784448,
            "min": 0.0045784448,
            "max": 0.004789222400000001,
            "count": 2
        }
    },
    "metadata": {
        "timer_format_version": "0.1.0",
        "start_time_seconds": "1759157192",
        "python_version": "3.10.11 (tags/v3.10.11:7d4cc5a, Apr  5 2023, 00:38:17) [MSC v.1929 64 bit (AMD64)]",
        "command_line_arguments": "C:\\Users\\asier.aurre\\Documents\\Reinforced Learning\\police-thief-rl\\.venv\\Scripts\\mlagents-learn training\\configs\\car_agent.yaml --run-id=run123 --train",
        "mlagents_version": "1.1.0",
        "mlagents_envs_version": "1.1.0",
        "communication_protocol_version": "1.5.0",
        "pytorch_version": "2.8.0+cpu",
        "numpy_version": "1.23.5",
        "end_time_seconds": "1759157353"
    },
    "total": 160.36607939999885,
    "count": 1,
    "self": 0.004521500002738321,
    "children": {
        "run_training.setup": {
            "total": 0.06640149999657297,
            "count": 1,
            "self": 0.06640149999657297
        },
        "TrainerController.start_learning": {
            "total": 160.29515639999954,
            "count": 1,
            "self": 0.07774219990824349,
            "children": {
                "TrainerController._reset_env": {
                    "total": 14.508381700001337,
                    "count": 1,
                    "self": 14.508381700001337
                },
                "TrainerController.advance": {
                    "total": 145.63680670009126,
                    "count": 5524,
                    "self": 0.07625419983742177,
                    "children": {
                        "env_step": {
                            "total": 144.0750383000668,
                            "count": 5524,
                            "self": 140.93596240030456,
                            "children": {
                                "SubprocessEnvManager._take_step": {
                                    "total": 3.085944799859135,
                                    "count": 5525,
                                    "self": 0.2096436000210815,
                                    "children": {
                                        "TorchPolicy.evaluate": {
                                            "total": 2.8763011998380534,
                                            "count": 5525,
                                            "self": 2.8763011998380534
                                        }
                                    }
                                },
                                "workers": {
                                    "total": 0.053131099903112045,
                                    "count": 5523,
                                    "self": 0.0,
                                    "children": {
                                        "worker_root": {
                                            "total": 45.13138270007039,
                                            "count": 5523,
                                            "is_parallel": true,
                                            "self": 9.317188700129918,
                                            "children": {
                                                "steps_from_proto": {
                                                    "total": 0.0004352000032668002,
                                                    "count": 2,
                                                    "is_parallel": true,
                                                    "self": 0.00015150000399444252,
                                                    "children": {
                                                        "_process_rank_one_or_two_observation": {
                                                            "total": 0.00028369999927235767,
                                                            "count": 4,
                                                            "is_parallel": true,
                                                            "self": 0.00028369999927235767
                                                        }
                                                    }
                                                },
                                                "UnityEnvironment.step": {
                                                    "total": 35.813758799937204,
                                                    "count": 5523,
                                                    "is_parallel": true,
                                                    "self": 0.29772409997531213,
                                                    "children": {
                                                        "UnityEnvironment._generate_step_input": {
                                                            "total": 0.23675820013522753,
                                                            "count": 5523,
                                                            "is_parallel": true,
                                                            "self": 0.23675820013522753
                                                        },
                                                        "communicator.exchange": {
                                                            "total": 34.574646999895776,
                                                            "count": 5523,
                                                            "is_parallel": true,
                                                            "self": 34.574646999895776
                                                        },
                                                        "steps_from_proto": {
                                                            "total": 0.7046294999308884,
                                                            "count": 5523,
                                                            "is_parallel": true,
                                                            "self": 0.35816849977345555,
                                                            "children": {
                                                                "_process_rank_one_or_two_observation": {
                                                                    "total": 0.34646100015743286,
                                                                    "count": 11046,
                                                                    "is_parallel": true,
                                                                    "self": 0.34646100015743286
                                                                }
                                                            }
                                                        }
                                                    }
                                                }
                                            }
                                        }
                                    }
                                }
                            }
                        },
                        "trainer_advance": {
                            "total": 1.4855142001870263,
                            "count": 5523,
                            "self": 0.08669340029155137,
                            "children": {
                                "process_trajectory": {
                                    "total": 0.2624191998911556,
                                    "count": 5523,
                                    "self": 0.2624191998911556
                                },
                                "_update_policy": {
                                    "total": 1.1364016000043193,
                                    "count": 2,
                                    "self": 0.41138269999282784,
                                    "children": {
                                        "TorchPPOOptimizer.update": {
                                            "total": 0.7250189000114915,
                                            "count": 198,
                                            "self": 0.7250189000114915
                                        }
                                    }
                                }
                            }
                        }
                    }
                },
                "TrainerController._save_models": {
                    "total": 0.07222579999870504,
                    "count": 1,
                    "self": 0.009572199996910058,
                    "children": {
                        "RLTrainer._checkpoint": {
                            "total": 0.06265360000179498,
                            "count": 1,
                            "self": 0.06265360000179498
                        }
                    }
                }
            }
        }
    }
}